llm_json_fixer/__init__.py
llm_json_fixer/llm_json_fixer.py
llm_json_fixer-1.0.1.dist-info/licenses/LICENSE
llm_json_fixer-1.0.1.dist-info/METADATA
llm_json_fixer-1.0.1.dist-info/WHEEL
llm_json_fixer-1.0.1.dist-info/top_level.txt
llm_json_fixer-1.0.1.dist-info/RECORD
