Metadata-Version: 2.4
Name: llm_json_fixer
Version: 1.0.1
Summary: A simple utility to fix malformed JSON from LLM outputs
Home-page: https://github.com/mdhasnainali/llm_json_fixer
Author: Md. Hasnain Ali
Author-email: "Md. Hasnain Ali" <mdhasnainali.01@gmail.com>
License-Expression: MIT
Project-URL: Homepage, https://github.com/mdhasnainali/llm_json_fixer
Project-URL: Repository, https://github.com/mdhasnainali/llm_json_fixer
Project-URL: Issues, https://github.com/mdhasnainali/llm_json_fixer/issues
Project-URL: Documentation, https://github.com/mdhasnainali/llm_json_fixer#readme
Keywords: json,llm,fix,repair,malformed,ai,chatgpt,claude
Classifier: Development Status :: 5 - Production/Stable
Classifier: Intended Audience :: Developers
Classifier: Operating System :: OS Independent
Classifier: Programming Language :: Python :: 3
Classifier: Programming Language :: Python :: 3.7
Classifier: Programming Language :: Python :: 3.8
Classifier: Programming Language :: Python :: 3.9
Classifier: Programming Language :: Python :: 3.10
Classifier: Programming Language :: Python :: 3.11
Classifier: Programming Language :: Python :: 3.12
Classifier: Topic :: Software Development :: Libraries :: Python Modules
Classifier: Topic :: Text Processing :: Markup :: HTML
Classifier: Topic :: Utilities
Requires-Python: >=3.7
License-File: LICENSE
Dynamic: author
Dynamic: home-page
Dynamic: license-file
Dynamic: requires-python
